adbpackagesmanager/README.MD
adbpackagesmanager/__init__.py
adbpackagesmanager/requirements.txt
adbpackagesmanager/thirdparty.json
adbpackagesmanager-0.10.dist-info/LICENSE.rst
adbpackagesmanager-0.10.dist-info/METADATA
adbpackagesmanager-0.10.dist-info/WHEEL
adbpackagesmanager-0.10.dist-info/top_level.txt
adbpackagesmanager-0.10.dist-info/RECORD
