Metadata-Version: 2.1
Name: adbpackagesmanager
Version: 0.10
Summary: Manages Android packages on a device through DataFrames
Home-page: https://github.com/hansalemaos/adbpackagesmanager
Author: Johannes Fischer
Author-email: aulasparticularesdealemaosp@gmail.com
License: MIT
Keywords: adb,DataFrame,pandas,android,automation
Classifier: Development Status :: 4 - Beta
Classifier: Programming Language :: Python :: 3 :: Only
Classifier: Programming Language :: Python :: 3.10
Classifier: Topic :: Software Development :: Libraries :: Python Modules
Classifier: Topic :: Utilities
License-File: LICENSE.rst
Requires-Dist: a-pandas-ex-apply-ignore-exceptions
Requires-Dist: pandas
Requires-Dist: touchtouch
Requires-Dist: usefuladb
Requires-Dist: windows-filepath
